jd_converter/__init__.py
jd_converter/converter_jdatetime.py
JdateConverter-0.1.2.dist-info/METADATA
JdateConverter-0.1.2.dist-info/WHEEL
JdateConverter-0.1.2.dist-info/top_level.txt
JdateConverter-0.1.2.dist-info/RECORD
