Metadata-Version: 2.1
Name: JdateConverter
Version: 0.1.2
Summary: A package for converting to and from Jalali datetime
Author: Mohammad Namjoo
Author-email: namjoo.mohammad111@gmail.com
Classifier: Programming Language :: Python :: 3
Classifier: License :: OSI Approved :: MIT License
Classifier: Operating System :: OS Independent
Requires-Python: >=3.1
Requires-Dist: jdatetime
Provides-Extra: dev
Requires-Dist: jdatetime >=4.0.0 ; extra == 'dev'
Requires-Dist: jalali-core >=4.0.0 ; extra == 'dev'
Requires-Dist: twine >=2.1.1 ; extra == 'dev'
